{
  "listings": [
    {
      "id": 1,
      "description": "heater",
      "image": "./images/heater.jpg",
      "location": "BROOKLYN"
    },
    {
      "id": 4,
      "description": "FREE Hundreds of DVD/CD Cases - Different Sizes and Colors",
      "image": "./images/dvd-cases.jpg",
      "location": "Prospect Heights"
    },
    {
      "id": 5,
      "description": "wood",
      "image": "./images/wood.jpg",
      "location": "Greenpoint"
    },
    {
      "id": 6,
      "description": "Beautiful couch",
      "image": "./images/couch.jpg",
      "location": "Bay Ridge"
    },
    {
      "id": 7,
      "description": "Treadmill Parts For Free",
      "image": "./images/treadmill.jpg",
      "location": "East Flatbush"
    },
    {
      "description": "dsfasdf",
      "image": "https://images.unsplash.com/photo-1559116315-702b0b4774ce?ixlib=rb-1.2.1&ixid=MnwxMjA3fDB8MHxwaG90by1wYWdlfHx8fGVufDB8fHx8&auto=format&fit=crop&w=2183&q=80",
      "location": "21312",
      "id": 8
    },
    {
      "description": "sdfds",
      "image": "https://images.unsplash.com/photo-1559116315-702b0b4774ce?ixlib=rb-1.2.1&ixid=MnwxMjA3fDB8MHxwaG90by1wYWdlfHx8fGVufDB8fHx8&auto=format&fit=crop&w=2183&q=80",
      "location": "21312",
      "id": 9
    }
  ]
}